test/__init__.py
test/test.py
w2vembeddings/__init__.py
w2vembeddings/embedding.py
w2vembeddings/managedb.py
w2vembeddings/w2vemb.py
w2vembeddings-0.1.2.dist-info/LICENSE
w2vembeddings-0.1.2.dist-info/METADATA
w2vembeddings-0.1.2.dist-info/WHEEL
w2vembeddings-0.1.2.dist-info/top_level.txt
w2vembeddings-0.1.2.dist-info/RECORD
